aws_glue_artifact/__init__.py
aws_glue_artifact/_version.py
aws_glue_artifact/api.py
aws_glue_artifact/model.py
aws_glue_artifact/paths.py
aws_glue_artifact/docs/__init__.py
aws_glue_artifact/tests/__init__.py
aws_glue_artifact/tests/helper.py
aws_glue_artifact/tests/mock_aws.py
aws_glue_artifact/vendor/__init__.py
aws_glue_artifact/vendor/build.py
aws_glue_artifact/vendor/hashes.py
aws_glue_artifact/vendor/pytest_cov_helper.py
aws_glue_artifact-0.2.1.dist-info/AUTHORS.rst
aws_glue_artifact-0.2.1.dist-info/LICENSE.txt
aws_glue_artifact-0.2.1.dist-info/METADATA
aws_glue_artifact-0.2.1.dist-info/WHEEL
aws_glue_artifact-0.2.1.dist-info/top_level.txt
aws_glue_artifact-0.2.1.dist-info/RECORD
